pretix_sofort/__init__.py
pretix_sofort/apps.py
pretix_sofort/models.py
pretix_sofort/payment.py
pretix_sofort/signals.py
pretix_sofort/sofort.py
pretix_sofort/urls.py
pretix_sofort/views.py
pretix_sofort/locale/django.pot
pretix_sofort/locale/ca/LC_MESSAGES/django.mo
pretix_sofort/locale/ca/LC_MESSAGES/django.po
pretix_sofort/locale/cs/LC_MESSAGES/django.mo
pretix_sofort/locale/cs/LC_MESSAGES/django.po
pretix_sofort/locale/de/LC_MESSAGES/django.mo
pretix_sofort/locale/de/LC_MESSAGES/django.po
pretix_sofort/locale/de_Informal/.gitkeep
pretix_sofort/locale/de_Informal/LC_MESSAGES/django.mo
pretix_sofort/locale/de_Informal/LC_MESSAGES/django.po
pretix_sofort/locale/el/LC_MESSAGES/django.mo
pretix_sofort/locale/el/LC_MESSAGES/django.po
pretix_sofort/locale/fi/LC_MESSAGES/django.mo
pretix_sofort/locale/fi/LC_MESSAGES/django.po
pretix_sofort/locale/hr/LC_MESSAGES/django.mo
pretix_sofort/locale/hr/LC_MESSAGES/django.po
pretix_sofort/locale/it/LC_MESSAGES/django.mo
pretix_sofort/locale/it/LC_MESSAGES/django.po
pretix_sofort/locale/ja/LC_MESSAGES/django.mo
pretix_sofort/locale/ja/LC_MESSAGES/django.po
pretix_sofort/locale/lv/LC_MESSAGES/django.mo
pretix_sofort/locale/lv/LC_MESSAGES/django.po
pretix_sofort/locale/nl/LC_MESSAGES/django.mo
pretix_sofort/locale/nl/LC_MESSAGES/django.po
pretix_sofort/locale/nl_Informal/LC_MESSAGES/django.mo
pretix_sofort/locale/nl_Informal/LC_MESSAGES/django.po
pretix_sofort/locale/pl/LC_MESSAGES/django.mo
pretix_sofort/locale/pl/LC_MESSAGES/django.po
pretix_sofort/locale/pl_Informal/LC_MESSAGES/django.mo
pretix_sofort/locale/pl_Informal/LC_MESSAGES/django.po
pretix_sofort/locale/pt/LC_MESSAGES/django.mo
pretix_sofort/locale/pt/LC_MESSAGES/django.po
pretix_sofort/locale/ru/LC_MESSAGES/django.mo
pretix_sofort/locale/ru/LC_MESSAGES/django.po
pretix_sofort/locale/si/LC_MESSAGES/django.mo
pretix_sofort/locale/si/LC_MESSAGES/django.po
pretix_sofort/locale/sl/LC_MESSAGES/django.mo
pretix_sofort/locale/sl/LC_MESSAGES/django.po
pretix_sofort-1.4.1.dist-info/LICENSE
pretix_sofort-1.4.1.dist-info/METADATA
pretix_sofort-1.4.1.dist-info/WHEEL
pretix_sofort-1.4.1.dist-info/entry_points.txt
pretix_sofort-1.4.1.dist-info/top_level.txt
pretix_sofort-1.4.1.dist-info/RECORD
