Metadata-Version: 2.1
Name: pretix-sofort
Version: 1.4.1
Summary: pretix payment via Klarna Sofort
Author-email: pretix team <support@pretix.eu>
Maintainer-email: pretix team <support@pretix.eu>
License: Copyright 2018 Raphael Michel
Project-URL: homepage, https://github.com/pretix/pretix-sofort
Keywords: pretix
Requires-Python: >=3.9
License-File: LICENSE
Requires-Dist: lxml
